sterai/__init__.py
sterai/main.py
sterai-1.1.0.dist-info/METADATA
sterai-1.1.0.dist-info/WHEEL
sterai-1.1.0.dist-info/entry_points.txt
sterai-1.1.0.dist-info/top_level.txt
sterai-1.1.0.dist-info/RECORD
