Metadata-Version: 2.4
Name: sterai
Version: 1.1.0
Summary: An AI-powered MCQ Analysis Tool
Home-page: https://github.com/knownme100/sterai
Author: KnownMe100
Author-email: knownme100@protonmail.com
Project-URL: Bug Tracker, https://github.com/knownme100/sterai/issues
Classifier: Programming Language :: Python :: 3
Classifier: License :: OSI Approved :: MIT License
Classifier: Operating System :: OS Independent
Classifier: Development Status :: 4 - Beta
Classifier: Intended Audience :: Education
Classifier: Topic :: Education :: Testing
Requires-Python: >=3.6
Requires-Dist: requests>=1.0.0
Dynamic: author
Dynamic: author-email
Dynamic: classifier
Dynamic: description
Dynamic: description-content-type
Dynamic: home-page
Dynamic: project-url
Dynamic: requires-dist
Dynamic: requires-python
Dynamic: summary
